MANIFEST.in
README.rst
setup.cfg
setup.py
frontoxy/__init__.py
frontoxy/queue.py
frontoxy.egg-info/PKG-INFO
frontoxy.egg-info/SOURCES.txt
frontoxy.egg-info/dependency_links.txt
frontoxy.egg-info/requires.txt
frontoxy.egg-info/top_level.txt
frontoxy/blacklist/__init__.py
frontoxy/blacklist/middlewares/__init__.py
frontoxy/blacklist/middlewares/luminati.py
frontoxy/blocks/__init__.py
frontoxy/blocks/reader.py
frontoxy/blocks/writer.py
frontoxy/frontier/__init__.py
frontoxy/frontier/canonical.py
frontoxy/frontier/queue.py
frontoxy/frontier/scheduler.py
frontoxy/frontier/utils.py
frontoxy/frontier/middlewares/__init__.py
frontoxy/frontier/middlewares/schedulers.py
frontoxy/spiders/__init__.py
frontoxy/spiders/base_spider.py