Metadata-Version: 1.1
Name: frontoxy
Version: 1.0.3
Summary: Distributed URLs frontier for Scrapy with RabbitMQ
Home-page: https://github.com/fabienvauchelles/frontoxy
Author: Fabien Vauchelles
Author-email: fabien@vauchelles.com
License: UNKNOWN
Download-URL: https://github.com/fabienvauchelles/frontoxy/tarball/1.0.3
Keywords: crawler,crawling,scrapoxy,scrapy,scraper,scraping,frontier
Platform: UNKNOWN
